{
    "replace": false,
    "slots": [
        "single/handle"
    ],
    "materialSlotCount": 1,
    "displayType": "major",
    "glyph": {
        "textureX": 112,
        "textureY": 32
    },
    "outcomes": [
        {
            "material": {
                "tag": "forge:ingots/quicksilver"
            },
            "requiredCapabilities": {
                "hammer": 1
            },
            "moduleKey": "single/long_handle",
            "moduleVariant": "long_handle/quicksilver"
        }
    ]
}